pyggm/__init__.py
pyggm/estimators/__init__.py
pyggm/estimators/ebic.py
pyggm/estimators/ggm.py
pyggm/estimators/stars.py
pyggm/preprocessing/__init__.py
pyggm/preprocessing/correlation.py
pyggm/preprocessing/nonparanormal.py
pyggm/utils/__init__.py
pyggm/utils/psd.py
pyggm/utils/validation.py
pyggm/visualization/__init__.py
pyggm/visualization/diagnostics.py
pyggm/visualization/matrix.py
pyggm/visualization/network.py
pyggm-0.1.2.dist-info/licenses/LICENSE
pyggm-0.1.2.dist-info/METADATA
pyggm-0.1.2.dist-info/WHEEL
pyggm-0.1.2.dist-info/top_level.txt
pyggm-0.1.2.dist-info/RECORD
