Metadata-Version: 2.4
Name: pyggm
Version: 0.1.2
Summary: Gaussian Graphical Models with StARS, EBIC, and Nonparanormal methods
Author-email: Nandini Prasad <nandini.prasad@columbia.edu>
License: MIT
Project-URL: Homepage, https://github.com/naandip/pyggm
Project-URL: Documentation, https://pyggm.readthedocs.io
Project-URL: Repository, https://github.com/naandip/pyggm
Keywords: graphical models,precision matrix,StARS,graphical lasso,network
Classifier: Development Status :: 3 - Alpha
Classifier: Intended Audience :: Science/Research
Classifier: License :: OSI Approved :: MIT License
Classifier: Programming Language :: Python :: 3
Classifier: Programming Language :: Python :: 3.9
Classifier: Programming Language :: Python :: 3.10
Classifier: Programming Language :: Python :: 3.11
Classifier: Programming Language :: Python :: 3.12
Classifier: Topic :: Scientific/Engineering :: Mathematics
Requires-Python: >=3.9
License-File: LICENSE
Requires-Dist: numpy>=1.20
Requires-Dist: scipy>=1.7
Requires-Dist: scikit-learn>=1.0
Requires-Dist: joblib>=1.0
Requires-Dist: networkx>=2.6
Requires-Dist: matplotlib>=3.4
Provides-Extra: dev
Requires-Dist: pytest>=7.0; extra == "dev"
Requires-Dist: pytest-cov>=4.0; extra == "dev"
Requires-Dist: black>=23.0; extra == "dev"
Requires-Dist: ruff>=0.1.0; extra == "dev"
Requires-Dist: mypy>=1.0; extra == "dev"
Provides-Extra: docs
Requires-Dist: sphinx>=6.0; extra == "docs"
Requires-Dist: sphinx-rtd-theme>=1.0; extra == "docs"
Requires-Dist: numpydoc>=1.5; extra == "docs"
Dynamic: license-file
